spro/.DS_Store
spro/__init__.py
spro/__main__.py
spro/_exceptions.py
spro/_models.py
spro/spro.py
spro-0.1.0b0.dist-info/METADATA
spro-0.1.0b0.dist-info/WHEEL
spro-0.1.0b0.dist-info/entry_points.txt
spro-0.1.0b0.dist-info/RECORD
