Metadata-Version: 2.1
Name: spro
Version: 0.1.0b0
Summary: Spro is a secure gateway to privacy-compliant AI interactions.
Author: HridaAI
Requires-Python: >=3.12,<4.0
Classifier: Programming Language :: Python :: 3
Classifier: Programming Language :: Python :: 3.12
Classifier: Programming Language :: Python :: 3.13
Requires-Dist: httpx (>=0.27.2,<0.28.0)
